chrome_cookiejar/__init__.py
chrome_cookiejar/decrypt.py
chrome_cookiejar/main.py
chrome_cookiejar/path.py
chrome_cookiejar/unix_crypt.py
chrome_cookiejar/win32crypt.py
chrome_cookiejar-0.1.0.dist-info/LICENSE
chrome_cookiejar-0.1.0.dist-info/METADATA
chrome_cookiejar-0.1.0.dist-info/WHEEL
chrome_cookiejar-0.1.0.dist-info/top_level.txt
chrome_cookiejar-0.1.0.dist-info/zip-safe
chrome_cookiejar-0.1.0.dist-info/RECORD
