Metadata-Version: 2.1
Name: chrome-cookiejar
Version: 0.1.0
Summary: Python library for retrieving cookies from the Chrome browser
Home-page: https://github.com/arnie97/chrome-cookiejar
Author: Arnie97
Author-email: arnie97@gmail.com
License: MIT License
Project-URL: Bug Tracker, https://github.com/arnie97/chrome-cookiejar/issues
Platform: UNKNOWN
Classifier: Programming Language :: Python :: 3 :: Only
Classifier: Programming Language :: Python :: 3.5
Classifier: License :: OSI Approved :: MIT License
Classifier: Operating System :: POSIX :: Linux
Classifier: Operating System :: MacOS
Classifier: Operating System :: Microsoft :: Windows
Classifier: Topic :: Internet :: WWW/HTTP :: Session
Classifier: Topic :: Software Development :: Libraries :: Python Modules
Requires-Python: >=3.5
Requires-Dist: pycryptodome ; os_name == "posix"
